elmax_api/__init__.py
elmax_api/constants.py
elmax_api/exceptions.py
elmax_api/http.py
elmax_api/model/__init__.py
elmax_api/model/actuator.py
elmax_api/model/alarm_status.py
elmax_api/model/area.py
elmax_api/model/command.py
elmax_api/model/cover.py
elmax_api/model/cover_status.py
elmax_api/model/endpoint.py
elmax_api/model/goup.py
elmax_api/model/panel.py
elmax_api/model/scene.py
elmax_api/model/zone.py
elmax_api/push/__init__.py
elmax_api/push/push.py
elmax_api-0.0.6.3.data/data/requirements.txt
elmax_api-0.0.6.3.dist-info/METADATA
elmax_api-0.0.6.3.dist-info/WHEEL
elmax_api-0.0.6.3.dist-info/top_level.txt
elmax_api-0.0.6.3.dist-info/RECORD
