Metadata-Version: 2.1
Name: elmax_api
Version: 0.0.6.3
Summary: Asynchronous API Library to work with Elmax devices
Home-page: https://github.com/albertogeniola/elmax-api
Author: Alberto Geniola
Author-email: albertogeniola@gmail.com
License: MIT
Project-URL: Documentation, https://github.com/albertogeniola/elmax-api
Project-URL: Source, https://github.com/albertogeniola/elmax-api
Project-URL: Tracker, https://github.com/albertogeniola/elmax-api
Classifier: Intended Audience :: Developers
Classifier: Programming Language :: Python :: 3
Classifier: Operating System :: OS Independent
Requires-Python: >=3.7
Requires-Dist: pyjwt>=1.7.1
Requires-Dist: httpx>=0.18.0
Requires-Dist: yarl>=1.6.3
Requires-Dist: websockets>=13.0
